quanmsms/__init__.py
quanmsms/example.py
quanmsms/sdk.py
quanmsms-0.2.1.dist-info/LICENSE
quanmsms-0.2.1.dist-info/METADATA
quanmsms-0.2.1.dist-info/WHEEL
quanmsms-0.2.1.dist-info/top_level.txt
quanmsms-0.2.1.dist-info/RECORD
