Metadata-Version: 2.1
Name: quanmsms
Version: 0.2.1
Summary: 发送短信,dev.quanmwl.com/ability_sms --> Python版SDK
Home-page: https://gitee.com/chengdu-quanming-network/quanmsms-python
Author: wubie
Author-email: qp@quanmwl.com
License: UNKNOWN
Platform: UNKNOWN
License-File: LICENSE
